doh_cli/__init__.py
doh_cli/resolve.py
doh_cli-0.8.data/scripts/doh-cli
doh_cli-0.8.dist-info/LICENSE
doh_cli-0.8.dist-info/METADATA
doh_cli-0.8.dist-info/WHEEL
doh_cli-0.8.dist-info/top_level.txt
doh_cli-0.8.dist-info/RECORD
