Metadata-Version: 2.2
Name: doh-cli
Version: 0.8
Summary: a simple DNS-over-HTTPS client
Home-page: https://gitlab.com/libreops/doh-cli
Author: LibreOps
Author-email: team@libreops.cc
License: LICENSE
Classifier: Development Status :: 5 - Production/Stable
Classifier: Environment :: Console
Classifier: License :: OSI Approved :: GNU General Public License v3 (GPLv3)
Classifier: Operating System :: OS Independent
Classifier: Programming Language :: Python :: 3 :: Only
Classifier: Topic :: Internet :: Name Service (DNS)
License-File: LICENSE
Requires-Dist: dnspython
Requires-Dist: requests
Dynamic: author
Dynamic: author-email
Dynamic: classifier
Dynamic: description
Dynamic: description-content-type
Dynamic: home-page
Dynamic: license
Dynamic: requires-dist
Dynamic: summary
